__init__.py
lmfitxtend/__init__.py
lmfitxtend/functions.py
lmfitxtend/models.py
lmfitxtended-1.0.0.dist-info/LICENSE
lmfitxtended-1.0.0.dist-info/METADATA
lmfitxtended-1.0.0.dist-info/WHEEL
lmfitxtended-1.0.0.dist-info/top_level.txt
lmfitxtended-1.0.0.dist-info/RECORD
