Metadata-Version: 2.1
Name: lmfitxtended
Version: 1.0.0
Summary: This package contains additional models for the lmfit package.
Author-email: Julian Hochhaus <julian.hochhaus@tu-dortmund.de>
License: MIT License
Project-URL: homepage, https://github.com/Julian-Hochhaus/lmfit-additional-models)
Project-URL: documentation, https://lmfit-additional-models.readthedocs.io/en/latest/#
License-File: LICENSE
